Workbook

Sheet Mode d'emploi
A1: Référentiel d'auto-évaluation BPP — SFPO
A2: Fichier maître : c'est ce fichier que l'outil importe. Toute évolution du questionnaire se fait ici.
A4: Version du référentiel | B4: 2026-10-08
A5: « Ancien code » se rapporte à la version | B5: 2026-10-07
A7: Feuille « Référentiel » | B7: Une ligne par titre ou par question, dans l'ordre d'affichage.
A8: Type | B8: Titre (chapitre / section) · Question (reçoit une réponse) · Intitulé commun (début de phrase partagé par ses sous-questions, sans réponse).
A9: Niveau | B9: Titres uniquement : 1 = chapitre (menu latéral), 2 = section, 3 à 5 = sous-sections.
A10: Code | B10: Unique. Format Q123, sous-question Q123.01, sous-sous-question Q123.01.02 (séparateur point).
A11: Ancien code | B11: À remplir si vous renumérotez ou fusionnez des questions : code(s) précédent(s), séparés par une virgule. Les réponses déjà saisies suivent ainsi la question. Laisser vide sinon.
A12: Question chapeau | B12: Rempli d'après le code (Q123.01 → Q123). Doit exister.
A13: Condition | B13: Question à laquelle il faut répondre (colonne G) et réponse attendue OUI ou NON (colonne H) pour afficher la question. « OUI » inclut « partiellement ».
A14: Réf. BPP | B14: Toutes les références, séparées par « , ». Chaque référence doit figurer dans la feuille « Références BPP ».
A15: Contrôle | B15: Calculé : doit valoir OK sur chaque question avant de transmettre le fichier.
A16: Sévérité | B16: Questions uniquement : Critique, Majeur ou Mineur (colonne M), impact potentiel d'un écart sur le patient, le personnel ou le produit ; colonne N : motif. Sert au verdict de l'onglet « Avis d'expert » et au rapport d'audit. Synthèse dans la feuille « Sévérités ».
... A24: Avant chaque nouvelle version | B24: 1) Changer « Version du référentiel » (ex. date du jour) ; 2) recopier l'ancienne version dans « « Ancien code » se rapporte à la version » ; 3) vider la colonne « Ancien code », puis ne la remplir que pour les questions renumérotées ou fusionnées. L'import refuse un fichier dont la version de référence ne correspond pas à celle en service.

Sheet Référentiel
A1: Ordre | B1: Type | C1: Niveau | D1: Code | E1: Ancien code | F1: Question chapeau | G1: Condition : question | H1: Condition : réponse | I1: Intitulé | J1: Réf. BPP | K1: Contrôle | L1: aide (masquée) | M1: Sévérité | N1: Motif de la sévérité
A2: 1 | B2: Titre | C2: 1 | I2: MANAGEMENT DU SYSTÈME QUALITÉ PHARMACEUTIQUE
A3: 2 | B3: Titre | C3: 2 | I3: PRINCIPES
A4: 3 | B4: Question | D4: Q001 | E4: S 01 | I4: Les préparations pharmaceutiques réalisées garantissent une qualité constante, appropriée à leur usage, conformément aux exigences des BPP | J4: 1.01 | K4: =IF(COUNTIF($D$2:$D$2000,D4)>1,"Code en double",IF(AND(F4<>"",COUNTIF($D$2:$D$2000,F4)=0),"Question chapeau inconnue",IF(AND(G4<>"",COUNTIF($D$2:$D$2000,G4)=0),"Condition inconnue",IF(G4=D4,"Dépend d'elle-même",IF(J4="","Aucune réf. BPP",IF(AND(B4="Question",M4=""),"Sévérité manquante","OK")))))) | L4: =", "&J4&"," | M4: Majeur | N4: Exigence générale de qualité constante des préparations
A5: 4 | B5: Question | D5: Q002 | E5: Q001 | I5: Il existe un Système d'Assurance Qualité | J5: 1.02 | K5: =IF(COUNTIF($D$2:$D$2000,D5)>1,"Code en double",IF(AND(F5<>"",COUNTIF($D$2:$D$2000,F5)=0),"Question chapeau inconnue",IF(AND(G5<>"",COUNTIF($D$2:$D$2000,G5)=0),"Condition inconnue",IF(G5=D5,"Dépend d'elle-même",IF(J5="","Aucune réf. BPP",IF(AND(B5="Question",M5=""),"Sévérité manquante","OK")))))) | L5: =", "&J5&"," | M5: Majeur | N5: Absence de système qualité compromet toute la maîtrise
A6: 5 | B6: Question | D6: Q003 | E6: Q002 | G6: Q002 | H6: OUI | I6: Ce système est documenté (MAQ, Procédures, Modes Opératoires, Enregistrements ...) | J6: 1.02 | K6: =IF(COUNTIF($D$2:$D$2000,D6)>1,"Code en double",IF(AND(F6<>"",COUNTIF($D$2:$D$2000,F6)=0),"Question chapeau inconnue",IF(AND(G6<>"",COUNTIF($D$2:$D$2000,G6)=0),"Condition inconnue",IF(G6=D6,"Dépend d'elle-même",IF(J6="","Aucune réf. BPP",IF(AND(B6="Question",M6=""),"Sévérité manquante","OK")))))) | L6: =", "&J6&"," | M6: Majeur | N6: Système qualité non documenté, pratiques non maîtrisées
A7: 6 | B7: Question | D7: Q004 | E7: Q003 | G7: Q002 | H7: OUI | I7: Ce système est controlé (auto-inspection, audits,..) | J7: 1.02, 1.05 | K7: =IF(COUNTIF($D$2:$D$2000,D7)>1,"Code en double",IF(AND(F7<>"",COUNTIF($D$2:$D$2000,F7)=0),"Question chapeau inconnue",IF(AND(G7<>"",COUNTIF($D$2:$D$2000,G7)=0),"Condition inconnue",IF(G7=D7,"Dépend d'elle-même",IF(J7="","Aucune réf. BPP",IF(AND(B7="Question",M7=""),"Sévérité manquante","OK")))))) | L7: =", "&J7&"," | M7: Majeur | N7: Absence d'audits empêche détection des dérives
A8: 7 | B8: Question | D8: Q005 | E8: Q004 | G8: Q002 | H8: OUI | I8: Des indicateurs qualités sont identifiés et suivis | J8: 1.02, 1.05 | K8: =IF(COUNTIF($D$2:$D$2000,D8)>1,"Code en double",IF(AND(F8<>"",COUNTIF($D$2:$D$2000,F8)=0),"Question chapeau inconnue",IF(AND(G8<>"",COUNTIF($D$2:$D$2000,G8)=0),"Condition inconnue",IF(G8=D8,"Dépend d'elle-même",IF(J8="","Aucune réf. BPP",IF(AND(B8="Question",M8=""),"Sévérité manquante","OK")))))) | L8: =", "&J8&"," | M8: Mineur | N8: Indicateurs qualité : outil de pilotage
A9: 8 | B9: Titre | C9: 2 | I9: SYSTÈME QUALITÉ PHARMACEUTIQUE
A10: 9 | B10: Question | D10: Q006 | E10: Q005 | G10: Q002 | H10: OUI | I10: Le Système d'Assurance Qualité est basé sur les "Bonnes Pratiques de Préparation" publiées par l'ANSM en 2023 (documents qualités intégrant les BPP) | J10: 1.03, 1.04, 1.06, 1.07, 1.02 | K10: =IF(COUNTIF($D$2:$D$2000,D10)>1,"Code en double",IF(AND(F10<>"",COUNTIF($D$2:$D$2000,F10)=0),"Question chapeau inconnue",IF(AND(G10<>"",COUNTIF($D$2:$D$2000,G10)=0),"Condition inconnue",IF(G10=D10,"Dépend d'elle-même",IF(J10="","Aucune réf. BPP",IF(AND(B10="Question",M10=""),"Sévérité manquante","OK")))))) | L10: =", "&J10&"," | M10: Mineur | N10: Référence documentaire aux BPP 2023
A11: 10 | B11: Question | D11: Q007 | E11: Q006 | I11: Il existe un Système de Gestion Documentaire | J11: 1.05 | K11: =IF(COUNTIF($D$2:$D$2000,D11)>1,"Code en double",IF(AND(F11<>"",COUNTIF($D$2:$D$2000,F11)=0),"Question chapeau inconnue",IF(AND(G11<>"",COUNTIF($D$2:$D$2000,G11)=0),"Condition inconnue",IF(G11=D11,"Dépend d'elle-même",IF(J11="","Aucune réf. BPP",IF(AND(B11="Question",M11=""),"Sévérité manquante","OK")))))) | L11: =", "&J11&"," | M11: Majeur | N11: Gestion documentaire indispensable à la maîtrise du système
A12: 11 | B12: Question | D12: Q008 | E12: Q007 | G12: Q002 | H12: OUI | I12: Le système d'assurance qualité est connu du personnel impliqué dans la production | J12: 1.05 | K12: =IF(COUNTIF($D$2:$D$2000,D12)>1,"Code en double",IF(AND(F12<>"",COUNTIF($D$2:$D$2000,F12)=0),"Question chapeau inconnue",IF(AND(G12<>"",COUNTIF($D$2:$D$2000,G12)=0),"Condition inconnue",IF(G12=D12,"Dépend d'elle-même",IF(J12="","Aucune réf. BPP",IF(AND(B12="Question",M12=""),"Sévérité manquante","OK")))))) | L12: =", "&J12&"," | M12: Majeur | N12: Personnel ignorant le système qualité
A13: 12 | B13: Question | D13: Q009 | E13: Q008 | I13: Les préparations pharmaceutiques sont formulées et réalisées selon l’état des connaissances scientifiques, médicales et pharmaceutiques et l'analyse y conduisant est tracée (exemple de dossier de préparation suivant annexe) | J13: 1.05 | K13: =IF(COUNTIF($D$2:$D$2000,D13)>1,"Code en double",IF(AND(F13<>"",COUNTIF($D$2:$D$2000,F13)=0),"Question chapeau inconnue",IF(AND(G13<>"",COUNTIF($D$2:$D$2000,G13)=0),"Condition inconnue",IF(G13=D13,"Dépend d'elle-même",IF(J13="","Aucune réf. BPP",IF(AND(B13="Question",M13=""),"Sévérité manquante","OK")))))) | L13: =", "&J13&"," | M13: Majeur | N13: Formulation non justifiée scientifiquement, traçabilité de l'analyse
A14: 13 | B14: Titre | C14: 2 | I14: BONNES PRATIQUES DE PRÉPARATION
A15: 14 | B15: Titre | C15: 2 | I15: REVUE QUALITÉ DES PRÉPARATIONS PHARMACEUTIQUES
A16: 15 | B16: Question | D16: Q010 | E16: Q009 | I16: Des revues qualité sont organisées selon une périodicité définie après analyse des réclamations et des non-conformité | J16: 1.10 | K16: =IF(COUNTIF($D$2:$D$2000,D16)>1,"Code en double",IF(AND(F16<>"",COUNTIF($D$2:$D$2000,F16)=0),"Question chapeau inconnue",IF(AND(G16<>"",COUNTIF($D$2:$D$2000,G16)=0),"Condition inconnue",IF(G16=D16,"Dépend d'elle-même",IF(J16="","Aucune réf. BPP",IF(AND(B16="Question",M16=""),"Sévérité manquante","OK")))))) | L16: =", "&J16&"," | M16: Mineur | N16: Revue qualité périodique
A17: 16 | B17: Question | D17: Q011 | E17: Q010 | G17: Q010 | H17: OUI | I17: Les revues qualités sont documentées | J17: 1.10 | K17: =IF(COUNTIF($D$2:$D$2000,D17)>1,"Code en double",IF(AND(F17<>"",COUNTIF($D$2:$D$2000,F17)=0),"Question chapeau inconnue",IF(AND(G17<>"",COUNTIF($D$2:$D$2000,G17)=0),"Condition inconnue",IF(G17=D17,"Dépend d'elle-même",IF(J17="","Aucune réf. BPP",IF(AND(B17="Question",M17=""),"Sévérité manquante","OK")))))) | L17: =", "&J17&"," | M17: Mineur | N17: Documentation des revues qualité
A18: 17 | B18: Question | D18: Q012 | E18: Q011 | G18: Q010 | H18: OUI | I18: Les revues qualités alimentent l'analyse globale de risque | J18: 1.10 | K18: =IF(COUNTIF($D$2:$D$2000,D18)>1,"Code en double",IF(AND(F18<>"",COUNTIF($D$2:$D$2000,F18)=0),"Question chapeau inconnue",IF(AND(G18<>"",COUNTIF($D$2:$D$2000,G18)=0),"Condition inconnue",IF(G18=D18,"Dépend d'elle-même",IF(J18="","Aucune réf. BPP",IF(AND(B18="Question",M18=""),"Sévérité manquante","OK")))))) | L18: =", "&J18&"," | M18: Mineur | N18: Lien revues qualité et analyse de risque
A19: 18 | B19: Titre | C19: 2 | I19: APPRÉCIATION DU RISQUE DE LA PRÉPARATION PHARMACEUTIQUE
A20: 19 | B20: Question | D20: Q013 | E20: Q012 | I20: L'appréciation du risque de la préparation pharmaceutique est réalisée (bénéfice/risque), permettant de décider si des mesures de réduction du risque doivent être mises en œuvre, ou si le risque existant peut être accepté | J20: 1.11 | K20: =IF(COUNTIF($D$2:$D$2000,D20)>1,"Code en double",IF(AND(F20<>"",COUNTIF($D$2:$D$2000,F20)=0),"Question chapeau inconnue",IF(AND(G20<>"",COUNTIF($D$2:$D$2000,G20)=0),"Condition inconnue",IF(G20=D20,"Dépend d'elle-même",IF(J20="","Aucune réf. BPP",IF(AND(B20="Question",M20=""),"Sévérité manquante","OK")))))) | L20: =", "&J20&"," | M20: Majeur | N20: Appréciation bénéfice/risque de la préparation
A21: 20 | B21: Question | D21: Q014 | E21: Q013 | I21: Une analyse pharmaceutique et réglementaire est réalisée pour chaque type de préparation (annexe I) | J21: 1.12 | K21: =IF(COUNTIF($D$2:$D$2000,D21)>1,"Code en double",IF(AND(F21<>"",COUNTIF($D$2:$D$2000,F21)=0),"Question chapeau inconnue",IF(AND(G21<>"",COUNTIF($D$2:$D$2000,G21)=0),"Condition inconnue",IF(G21=D21,"Dépend d'elle-même",IF(J21="","Aucune réf. BPP",IF(AND(B21="Question",M21=""),"Sévérité manquante","OK")))))) | L21: =", "&J21&"," | M21: Majeur | N21: Analyse pharmaceutique et réglementaire par type de préparation
A22: 21 | B22: Question | D22: Q015 | E22: Q014 | G22: Q014 | H22: OUI | I22: L'analyse pharmaceutique et réglementaire pour chaque type de préparation (annexe I) est réalisée et en cas de refus un critère explicite est tracé pour justifier la non réalisation | J22: 1.20 | K22: =IF(COUNTIF($D$2:$D$2000,D22)>1,"Code en double",IF(AND(F22<>"",COUNTIF($D$2:$D$2000,F22)=0),"Question chapeau inconnue",IF(AND(G22<>"",COUNTIF($D$2:$D$2000,G22)=0),"Condition inconnue",IF(G22=D22,"Dépend d'elle-même",IF(J22="","Aucune réf. BPP",IF(AND(B22="Question",M22=""),"Sévérité manquante","OK")))))) | L22: =", "&J22&"," | M22: Mineur | N22: Traçabilité du motif de refus
A23: 22 | B23: Question | D23: Q016 | E23: Q015 | I23: En cas d’impossibilité de réalisation de préparation, un contrat de sous-traitance est établi en amont, selon les modalités décrites par par le présent texte. | J23: 1.19 | K23: =IF(COUNTIF($D$2:$D$2000,D23)>1,"Code en double",IF(AND(F23<>"",COUNTIF($D$2:$D$2000,F23)=0),"Question chapeau inconnue",IF(AND(G23<>"",COUNTIF($D$2:$D$2000,G23)=0),"Condition inconnue",IF(G23=D23,"Dépend d'elle-même",IF(J23="","Aucune réf. BPP",IF(AND(B23="Question",M23=""),"Sévérité manquante","OK")))))) | L23: =", "&J23&"," | M23: Majeur | N23: Contrat de sous-traitance préalable
A24: 23 | B24: Question | D24: Q017 | E24: Q016 | I24: En cas d’impossibilité de réalisation d'une préparation, la notification et/ou proposition d'alternative au prescripteur est tracée | J24: 1.21 | K24: =IF(COUNTIF($D$2:$D$2000,D24)>1,"Code en double",IF(AND(F24<>"",COUNTIF($D$2:$D$2000,F24)=0),"Question chapeau inconnue",IF(AND(G24<>"",COUNTIF($D$2:$D$2000,G24)=0),"Condition inconnue",IF(G24=D24,"Dépend d'elle-même",IF(J24="","Aucune réf. BPP",IF(AND(B24="Question",M24=""),"Sévérité manquante","OK")))))) | L24: =", "&J24&"," | M24: Mineur | N24: Traçabilité de la notification au prescripteur
A25: 24 | B25: Question | D25: Q018 | E25: Q017 | I25: Une analyse de risque simplifiée est réalisée pour les préparations demandées en urgence | J25: 1.22 | K25: =IF(COUNTIF($D$2:$D$2000,D25)>1,"Code en double",IF(AND(F25<>"",COUNTIF($D$2:$D$2000,F25)=0),"Question chapeau inconnue",IF(AND(G25<>"",COUNTIF($D$2:$D$2000,G25)=0),"Condition inconnue",IF(G25=D25,"Dépend d'elle-même",IF(J25="","Aucune réf. BPP",IF(AND(B25="Question",M25=""),"Sévérité manquante","OK")))))) | L25: =", "&J25&"," | M25: Majeur | N25: Analyse de risque des préparations urgentes
A26: 25 | B26: Question | D26: Q019 | E26: Q018 | G26: Q014 | H26: OUI | I26: L'analyse technico-réglementaire des préparations est réalisée (annexe II partie 1) avant toute décision de réalisation | J26: 1.13, 1.15, 5.41 | K26: =IF(COUNTIF($D$2:$D$2000,D26)>1,"Code en double",IF(AND(F26<>"",COUNTIF($D$2:$D$2000,F26)=0),"Question chapeau inconnue",IF(AND(G26<>"",COUNTIF($D$2:$D$2000,G26)=0),"Condition inconnue",IF(G26=D26,"Dépend d'elle-même",IF(J26="","Aucune réf. BPP",IF(AND(B26="Question",M26=""),"Sévérité manquante","OK")))))) | L26: =", "&J26&"," | M26: Majeur | N26: Analyse technico-réglementaire avant réalisation
A27: 26 | B27: Question | D27: Q020 | E27: Q019 | G27: Q014 | H27: OUI | I27: L'analyse technico-réglementaire des préparations prend en compte la réglementation en vigueur (interdictions, restrictions, Formulaire National…) | J27: 1.17 | K27: =IF(COUNTIF($D$2:$D$2000,D27)>1,"Code en double",IF(AND(F27<>"",COUNTIF($D$2:$D$2000,F27)=0),"Question chapeau inconnue",IF(AND(G27<>"",COUNTIF($D$2:$D$2000,G27)=0),"Condition inconnue",IF(G27=D27,"Dépend d'elle-même",IF(J27="","Aucune réf. BPP",IF(AND(B27="Question",M27=""),"Sévérité manquante","OK")))))) | L27: =", "&J27&"," | M27: Majeur | N27: Prise en compte des interdictions réglementaires
A28: 27 | B28: Question | D28: Q021 | E28: Q020 | I28: Des analyses de risques concernant l'intégralité du processus de préparation sont réalisées (annexe III) | J28: 1.11, 4.05, 5.13, 5.23 | K28: =IF(COUNTIF($D$2:$D$2000,D28)>1,"Code en double",IF(AND(F28<>"",COUNTIF($D$2:$D$2000,F28)=0),"Question chapeau inconnue",IF(AND(G28<>"",COUNTIF($D$2:$D$2000,G28)=0),"Condition inconnue",IF(G28=D28,"Dépend d'elle-même",IF(J28="","Aucune réf. BPP",IF(AND(B28="Question",M28=""),"Sévérité manquante","OK")))))) | L28: =", "&J28&"," | M28: Majeur | N28: Analyse de risque du processus de préparation
A29: 28 | B29: Question | D29: Q022 | E29: Q021 | I29: Une analyse de risque est réalisée pour classer la préparation en risque faible, moyen ou élevé, selon les critères de l'annexe III (substance active, voie d'administration, forme pharmaceutique, opérations réalisées, nombre de patients), permettant de la classer en risque faible, moyen ou élevé | J29: 1.16, 5.23 | K29: =IF(COUNTIF($D$2:$D$2000,D29)>1,"Code en double",IF(AND(F29<>"",COUNTIF($D$2:$D$2000,F29)=0),"Question chapeau inconnue",IF(AND(G29<>"",COUNTIF($D$2:$D$2000,G29)=0),"Condition inconnue",IF(G29=D29,"Dépend d'elle-même",IF(J29="","Aucune réf. BPP",IF(AND(B29="Question",M29=""),"Sévérité manquante","OK")))))) | L29: =", "&J29&"," | M29: Majeur | N29: Classement du niveau de risque de la préparation
A30: 29 | B30: Question | D30: Q023 | E30: Q022 | G30: Q022 | H30: OUI | I30: Dans le cadre de l'analyse de risque pour classer la préparation, le niveau de risque « produit » (contamination microbiologique pour le patient) et le niveau de risque « personnel/environnement » (toxicité, CMR, produits biologiques/OGM) sont identifiés et distingués pour chaque produit. | J30: LD1.026 | K30: =IF(COUNTIF($D$2:$D$2000,D30)>1,"Code en double",IF(AND(F30<>"",COUNTIF($D$2:$D$2000,F30)=0),"Question chapeau inconnue",IF(AND(G30<>"",COUNTIF($D$2:$D$2000,G30)=0),"Condition inconnue",IF(G30=D30,"Dépend d'elle-même",IF(J30="","Aucune réf. BPP",IF(AND(B30="Question",M30=""),"Sévérité manquante","OK")))))) | L30: =", "&J30&"," | M30: Majeur | N30: Distinction risque produit et risque personnel
A31: 30 | B31: Question | D31: Q024 | E31: Q023 | I31: Une analyse de risque toxicologique de la préparation est réalisée, appuyée sur une recherche bibliographique sur les substances actives et excipients | J31: 4.32 | K31: =IF(COUNTIF($D$2:$D$2000,D31)>1,"Code en double",IF(AND(F31<>"",COUNTIF($D$2:$D$2000,F31)=0),"Question chapeau inconnue",IF(AND(G31<>"",COUNTIF($D$2:$D$2000,G31)=0),"Condition inconnue",IF(G31=D31,"Dépend d'elle-même",IF(J31="","Aucune réf. BPP",IF(AND(B31="Question",M31=""),"Sévérité manquante","OK")))))) | L31: =", "&J31&"," | M31: Majeur | N31: Analyse toxicologique des substances et excipients
A32: 31 | B32: Question | D32: Q025 | E32: Q024 | I32: Une analyse de risque relative à la réattribution des préparations est réalisée | J32: 5.61, 5.63 | K32: =IF(COUNTIF($D$2:$D$2000,D32)>1,"Code en double",IF(AND(F32<>"",COUNTIF($D$2:$D$2000,F32)=0),"Question chapeau inconnue",IF(AND(G32<>"",COUNTIF($D$2:$D$2000,G32)=0),"Condition inconnue",IF(G32=D32,"Dépend d'elle-même",IF(J32="","Aucune réf. BPP",IF(AND(B32="Question",M32=""),"Sévérité manquante","OK")))))) | L32: =", "&J32&"," | M32: Majeur | N32: Analyse de risque de la réattribution
A33: 32 | B33: Question | D33: Q026 | E33: Q025 | G33: Q022 | H33: OUI | I33: Le niveau de contrôle qualité appliqué est justifié par référence à l'analyse de risque réalisée pour chaque préparation de la préparation (cf. art. 1.16) | J33: 6.59 | K33: =IF(COUNTIF($D$2:$D$2000,D33)>1,"Code en double",IF(AND(F33<>"",COUNTIF($D$2:$D$2000,F33)=0),"Question chapeau inconnue",IF(AND(G33<>"",COUNTIF($D$2:$D$2000,G33)=0),"Condition inconnue",IF(G33=D33,"Dépend d'elle-même",IF(J33="","Aucune réf. BPP",IF(AND(B33="Question",M33=""),"Sévérité manquante","OK")))))) | L33: =", "&J33&"," | M33: Majeur | N33: Niveau de contrôle justifié par analyse de risque
A34: 33 | B34: Question | D34: Q027 | E34: Q026 | I34: Une analyse du risque d'interactions contenant-contenu est conduite (excipients à risque, données littérature/fournisseur/internes), avec recherche documentée de l'absence d'interaction. | J34: 6.85 | K34: =IF(COUNTIF($D$2:$D$2000,D34)>1,"Code en double",IF(AND(F34<>"",COUNTIF($D$2:$D$2000,F34)=0),"Question chapeau inconnue",IF(AND(G34<>"",COUNTIF($D$2:$D$2000,G34)=0),"Condition inconnue",IF(G34=D34,"Dépend d'elle-même",IF(J34="","Aucune réf. BPP",IF(AND(B34="Question",M34=""),"Sévérité manquante","OK")))))) | L34: =", "&J34&"," | M34: Majeur | N34: Analyse des interactions contenant-contenu
A35: 34 | B35: Question | D35: Q028 | E35: Q027 | I35: Une analyse de risque est réalisée pour la conception et de l’aménagement des locaux (matière première utilisée /procédé utilisé) | J35: 3.19, 5.18, 5.19, 5.20, 5.21, 5.22 | K35: =IF(COUNTIF($D$2:$D$2000,D35)>1,"Code en double",IF(AND(F35<>"",COUNTIF($D$2:$D$2000,F35)=0),"Question chapeau inconnue",IF(AND(G35<>"",COUNTIF($D$2:$D$2000,G35)=0),"Condition inconnue",IF(G35=D35,"Dépend d'elle-même",IF(J35="","Aucune réf. BPP",IF(AND(B35="Question",M35=""),"Sévérité manquante","OK")))))) | L35: =", "&J35&"," | M35: Majeur | N35: Analyse de risque pour la conception des locaux
A36: 35 | B36: Question | D36: Q029 | E36: Q028 | I36: Une analyse de risque documentée justifie le d'une choix zone (plutôt que local dédié) pour les catégories 1-3 non stériles/non CMR | J36: 3.15 | K36: =IF(COUNTIF($D$2:$D$2000,D36)>1,"Code en double",IF(AND(F36<>"",COUNTIF($D$2:$D$2000,F36)=0),"Question chapeau inconnue",IF(AND(G36<>"",COUNTIF($D$2:$D$2000,G36)=0),"Condition inconnue",IF(G36=D36,"Dépend d'elle-même",IF(J36="","Aucune réf. BPP",IF(AND(B36="Question",M36=""),"Sévérité manquante","OK")))))) | L36: =", "&J36&"," | M36: Mineur | N36: Justification documentée zone versus local dédié
A37: 36 | B37: Question | D37: Q030 | E37: Q029 | I37: La stratégie de libération repose sur une évaluation du risque formalisée et documentée. | J37: 6.70 | K37: =IF(COUNTIF($D$2:$D$2000,D37)>1,"Code en double",IF(AND(F37<>"",COUNTIF($D$2:$D$2000,F37)=0),"Question chapeau inconnue",IF(AND(G37<>"",COUNTIF($D$2:$D$2000,G37)=0),"Condition inconnue",IF(G37=D37,"Dépend d'elle-même",IF(J37="","Aucune réf. BPP",IF(AND(B37="Question",M37=""),"Sévérité manquante","OK")))))) | L37: =", "&J37&"," | M37: Majeur | N37: Stratégie de libération fondée sur le risque
A38: 37 | B38: Question | D38: Q031 | E38: Q030 | I38: Une analyse de risque préalable et documentée est réalisée pour le choix des installations et des équipements de préparation stérile | J38: LD1.034, 5.18, 5.19, 5.20, 5.21, 5.22 | K38: =IF(COUNTIF($D$2:$D$2000,D38)>1,"Code en double",IF(AND(F38<>"",COUNTIF($D$2:$D$2000,F38)=0),"Question chapeau inconnue",IF(AND(G38<>"",COUNTIF($D$2:$D$2000,G38)=0),"Condition inconnue",IF(G38=D38,"Dépend d'elle-même",IF(J38="","Aucune réf. BPP",IF(AND(B38="Question",M38=""),"Sévérité manquante","OK")))))) | L38: =", "&J38&"," | M38: Majeur | N38: Analyse de risque choix équipements stériles
A39: 38 | B39: Question | D39: Q032 | E39: Q031 | G39: Q031 | H39: OUI | I39: L'analyse de risque pour le choix des équipement et l'environnement se base sur les niveaux de risque produit et de la nature des manipulations | J39: LD1.027, LD1.028, LD1.029, LD1.030, LD1.031 | K39: =IF(COUNTIF($D$2:$D$2000,D39)>1,"Code en double",IF(AND(F39<>"",COUNTIF($D$2:$D$2000,F39)=0),"Question chapeau inconnue",IF(AND(G39<>"",COUNTIF($D$2:$D$2000,G39)=0),"Condition inconnue",IF(G39=D39,"Dépend d'elle-même",IF(J39="","Aucune réf. BPP",IF(AND(B39="Question",M39=""),"Sévérité manquante","OK")))))) | L39: =", "&J39&"," | M39: Majeur | N39: Critères de l'analyse de risque équipements
A40: 39 | B40: Question | D40: Q033 | E40: Q032 | I40: Une analyse de risque préalable est réalisée pour le procédé de stérilisation de contact à l'intérieur de l'isolateur | J40: LD1.076 | K40: =IF(COUNTIF($D$2:$D$2000,D40)>1,"Code en double",IF(AND(F40<>"",COUNTIF($D$2:$D$2000,F40)=0),"Question chapeau inconnue",IF(AND(G40<>"",COUNTIF($D$2:$D$2000,G40)=0),"Condition inconnue",IF(G40=D40,"Dépend d'elle-même",IF(J40="","Aucune réf. BPP",IF(AND(B40="Question",M40=""),"Sévérité manquante","OK")))))) | L40: =", "&J40&"," | M40: Majeur | N40: Analyse de risque stérilisation de contact isolateur
A41: 40 | B41: Question | D41: Q034 | E41: Q033 | I41: Une analyse de risques est réalisée pour l'élaboration du plan d'échantillonnage | J41: LD1.150 | K41: =IF(COUNTIF($D$2:$D$2000,D41)>1,"Code en double",IF(AND(F41<>"",COUNTIF($D$2:$D$2000,F41)=0),"Question chapeau inconnue",IF(AND(G41<>"",COUNTIF($D$2:$D$2000,G41)=0),"Condition inconnue",IF(G41=D41,"Dépend d'elle-même",IF(J41="","Aucune réf. BPP",IF(AND(B41="Question",M41=""),"Sévérité manquante","OK")))))) | L41: =", "&J41&"," | M41: Majeur | N41: Analyse de risque du plan d'échantillonnage
A42: 41 | B42: Question | D42: Q035 | E42: Q034 | I42: Une analyse de risque est réalisée si les limites de surveillance microbiologique des ZAC ne tiennent pas compte des recommandations décrites dans le tableau 9 (LD1) | J42: LD1.154 | K42: =IF(COUNTIF($D$2:$D$2000,D42)>1,"Code en double",IF(AND(F42<>"",COUNTIF($D$2:$D$2000,F42)=0),"Question chapeau inconnue",IF(AND(G42<>"",COUNTIF($D$2:$D$2000,G42)=0),"Condition inconnue",IF(G42=D42,"Dépend d'elle-même",IF(J42="","Aucune réf. BPP",IF(AND(B42="Question",M42=""),"Sévérité manquante","OK")))))) | L42: =", "&J42&"," | M42: Majeur | N42: Justification des limites microbiologiques des ZAC
A43: 42 | B43: Question | D43: Q036 | E43: Q035 | I43: Une analyse des risques professionnels est réalisé par l'employeur | J43: LD2.012 | K43: =IF(COUNTIF($D$2:$D$2000,D43)>1,"Code en double",IF(AND(F43<>"",COUNTIF($D$2:$D$2000,F43)=0),"Question chapeau inconnue",IF(AND(G43<>"",COUNTIF($D$2:$D$2000,G43)=0),"Condition inconnue",IF(G43=D43,"Dépend d'elle-même",IF(J43="","Aucune réf. BPP",IF(AND(B43="Question",M43=""),"Sévérité manquante","OK")))))) | L43: =", "&J43&"," | M43: Majeur | N43: Évaluation des risques professionnels obligatoire
A44: 43 | B44: Question | D44: Q037 | E44: Q036 | G44: Q036 | H44: OUI | I44: L'analyse des risques professionnels permet l'élaboration du Document Unique des Risques Professionnes (DUERP), accessible par l'ensemble du personnel | J44: LD2.012 | K44: =IF(COUNTIF($D$2:$D$2000,D44)>1,"Code en double",IF(AND(F44<>"",COUNTIF($D$2:$D$2000,F44)=0),"Question chapeau inconnue",IF(AND(G44<>"",COUNTIF($D$2:$D$2000,G44)=0),"Condition inconnue",IF(G44=D44,"Dépend d'elle-même",IF(J44="","Aucune réf. BPP",IF(AND(B44="Question",M44=""),"Sévérité manquante","OK")))))) | L44: =", "&J44&"," | M44: Mineur | N44: Formalisation et accessibilité du DUERP
A45: 44 | B45: Question | D45: Q038 | E45: Q037 | G45: Q036 | H45: OUI | I45: Le PRP est associé à la réalisation et l'actualisation du DUERP | J45: LD2.012 | K45: =IF(COUNTIF($D$2:$D$2000,D45)>1,"Code en double",IF(AND(F45<>"",COUNTIF($D$2:$D$2000,F45)=0),"Question chapeau inconnue",IF(AND(G45<>"",COUNTIF($D$2:$D$2000,G45)=0),"Condition inconnue",IF(G45=D45,"Dépend d'elle-même",IF(J45="","Aucune réf. BPP",IF(AND(B45="Question",M45=""),"Sévérité manquante","OK")))))) | L45: =", "&J45&"," | M45: Mineur | N45: Association du PRP au DUERP
A46: 45 | B46: Question | D46: Q039 | E46: Q038 | I46: Une analyse de risque est réalisée, le cas écheant si un même équipement est partagé entre préparations biologiques et chimiques non CMR | J46: LD2.019 | K46: =IF(COUNTIF($D$2:$D$2000,D46)>1,"Code en double",IF(AND(F46<>"",COUNTIF($D$2:$D$2000,F46)=0),"Question chapeau inconnue",IF(AND(G46<>"",COUNTIF($D$2:$D$2000,G46)=0),"Condition inconnue",IF(G46=D46,"Dépend d'elle-même",IF(J46="","Aucune réf. BPP",IF(AND(B46="Question",M46=""),"Sévérité manquante","OK")))))) | L46: =", "&J46&"," | M46: Majeur | N46: Risque de contamination croisée équipement partagé
A47: 46 | B47: Question | D47: Q040 | E47: Q039 | I47: Une analyse de risque spécifique est réalisée pour les manipulations présentant un risque de dispersion d'OGM | J47: LD2.021 | K47: =IF(COUNTIF($D$2:$D$2000,D47)>1,"Code en double",IF(AND(F47<>"",COUNTIF($D$2:$D$2000,F47)=0),"Question chapeau inconnue",IF(AND(G47<>"",COUNTIF($D$2:$D$2000,G47)=0),"Condition inconnue",IF(G47=D47,"Dépend d'elle-même",IF(J47="","Aucune réf. BPP",IF(AND(B47="Question",M47=""),"Sévérité manquante","OK")))))) | L47: =", "&J47&"," | M47: Majeur | N47: Analyse de risque dispersion d'OGM
A48: 47 | B48: Question | D48: Q041 | E48: Q040 | I48: Une analyse de risque est réalisée pour le choix des EPC / EPI en fonction du type de substances manipulées | J48: LD2.015, LD2.036, LD2.041, LD2.042 | K48: =IF(COUNTIF($D$2:$D$2000,D48)>1,"Code en double",IF(AND(F48<>"",COUNTIF($D$2:$D$2000,F48)=0),"Question chapeau inconnue",IF(AND(G48<>"",COUNTIF($D$2:$D$2000,G48)=0),"Condition inconnue",IF(G48=D48,"Dépend d'elle-même",IF(J48="","Aucune réf. BPP",IF(AND(B48="Question",M48=""),"Sévérité manquante","OK")))))) | L48: =", "&J48&"," | M48: Majeur | N48: Choix des EPC/EPI selon substances
A49: 48 | B49: Question | D49: Q042 | E49: Q041 | I49: Une analyse des risques est réalisée pour déterminer la fréquence de changement des gants | J49: LD2.040 | K49: =IF(COUNTIF($D$2:$D$2000,D49)>1,"Code en double",IF(AND(F49<>"",COUNTIF($D$2:$D$2000,F49)=0),"Question chapeau inconnue",IF(AND(G49<>"",COUNTIF($D$2:$D$2000,G49)=0),"Condition inconnue",IF(G49=D49,"Dépend d'elle-même",IF(J49="","Aucune réf. BPP",IF(AND(B49="Question",M49=""),"Sévérité manquante","OK")))))) | L49: =", "&J49&"," | M49: Majeur | N49: Fréquence de changement des gants
A50: 49 | B50: Titre | C50: 1 | I50: DOCUMENTATION
A51: 50 | B51: Titre | C51: 2 | I51: PRINCIPES
A52: 51 | B52: Intitulé commun | D52: Q043 | E52: Q042 | G52: Q007 | H52: OUI | I52: Le système documentaire mis en place (papier ou électronique) est | J52: 4.01, 4.06 | K52: =IF(COUNTIF($D$2:$D$2000,D52)>1,"Code en double",IF(AND(F52<>"",COUNTIF($D$2:$D$2000,F52)=0),"Question chapeau inconnue",IF(AND(G52<>"",COUNTIF($D$2:$D$2000,G52)=0),"Condition inconnue",IF(G52=D52,"Dépend d'elle-même",IF(J52="","Aucune réf. BPP",IF(AND(B52="Question",M52=""),"Sévérité manquante","OK")))))) | L52: =", "&J52&","
A53: 52 | B53: Question | D53: Q043.01 | E53: Q042.01 | F53: Q043 | G53: Q007 | H53: OUI | I53: protégé pour éviter toute modification non autorisée | J53: 4.01, 4.06 | K53: =IF(COUNTIF($D$2:$D$2000,D53)>1,"Code en double",IF(AND(F53<>"",COUNTIF($D$2:$D$2000,F53)=0),"Question chapeau inconnue",IF(AND(G53<>"",COUNTIF($D$2:$D$2000,G53)=0),"Condition inconnue",IF(G53=D53,"Dépend d'elle-même",IF(J53="","Aucune réf. BPP",IF(AND(B53="Question",M53=""),"Sévérité manquante","OK")))))) | L53: =", "&J53&"," | M53: Majeur | N53: Protection contre modifications non autorisées des données
A54: 53 | B54: Question | D54: Q043.02 | E54: Q042.02 | F54: Q043 | G54: Q007 | H54: OUI | I54: sauvegardé sur un 2ème support de sauvegarde pour éviter la perte de données | J54: 4.01 | K54: =IF(COUNTIF($D$2:$D$2000,D54)>1,"Code en double",IF(AND(F54<>"",COUNTIF($D$2:$D$2000,F54)=0),"Question chapeau inconnue",IF(AND(G54<>"",COUNTIF($D$2:$D$2000,G54)=0),"Condition inconnue",IF(G54=D54,"Dépend d'elle-même",IF(J54="","Aucune réf. BPP",IF(AND(B54="Question",M54=""),"Sévérité manquante","OK")))))) | L54: =", "&J54&"," | M54: Majeur | N54: Sauvegarde pour éviter perte de données
A55: 54 | B55: Question | D55: Q043.03 | E55: Q042.03 | F55: Q043 | G55: Q007 | H55: OUI | I55: et les données restent disponible pendant toute la durée de conservation exigée par les documents | J55: 4.01 | K55: =IF(COUNTIF($D$2:$D$2000,D55)>1,"Code en double",IF(AND(F55<>"",COUNTIF($D$2:$D$2000,F55)=0),"Question chapeau inconnue",IF(AND(G55<>"",COUNTIF($D$2:$D$2000,G55)=0),"Condition inconnue",IF(G55=D55,"Dépend d'elle-même",IF(J55="","Aucune réf. BPP",IF(AND(B55="Question",M55=""),"Sévérité manquante","OK")))))) | L55: =", "&J55&"," | M55: Mineur | N55: Disponibilité des données pendant la conservation
A56: 55 | B56: Question | D56: Q044 | E56: Q043 | G56: Q007 | H56: OUI | I56: L'ensemble de la documentation nécessaire et relative à l'activité du personnel (dossier papier ou logiciel de gestion documentaire) est rapidement accessible | J56: 4.01 | K56: =IF(COUNTIF($D$2:$D$2000,D56)>1,"Code en double",IF(AND(F56<>"",COUNTIF($D$2:$D$2000,F56)=0),"Question chapeau inconnue",IF(AND(G56<>"",COUNTIF($D$2:$D$2000,G56)=0),"Condition inconnue",IF(G56=D56,"Dépend d'elle-même",IF(J56="","Aucune réf. BPP",IF(AND(B56="Question",M56=""),"Sévérité manquante","OK")))))) | L56: =", "&J56&"," | M56: Mineur | N56: Accessibilité rapide de la documentation
A57: 56 | B57: Question | D57: Q045 | E57: Q044 | G57: Q007 | H57: OUI | I57: Il existe un logiciel de gestion documentaire | J57: 4.03 | K57: =IF(COUNTIF($D$2:$D$2000,D57)>1,"Code en double",IF(AND(F57<>"",COUNTIF($D$2:$D$2000,F57)=0),"Question chapeau inconnue",IF(AND(G57<>"",COUNTIF($D$2:$D$2000,G57)=0),"Condition inconnue",IF(G57=D57,"Dépend d'elle-même",IF(J57="","Aucune réf. BPP",IF(AND(B57="Question",M57=""),"Sévérité manquante","OK")))))) | L57: =", "&J57&"," | M57: Mineur | N57: Outil logiciel de gestion documentaire
A58: 57 | B58: Question | D58: Q046 | E58: Q045 | G58: Q045 | H58: OUI | I58: La sauvegarde et restauration du logiciel de gestion documentaire est testée et vérifiée | J58: 4.01 | K58: =IF(COUNTIF($D$2:$D$2000,D58)>1,"Code en double",IF(AND(F58<>"",COUNTIF($D$2:$D$2000,F58)=0),"Question chapeau inconnue",IF(AND(G58<>"",COUNTIF($D$2:$D$2000,G58)=0),"Condition inconnue",IF(G58=D58,"Dépend d'elle-même",IF(J58="","Aucune réf. BPP",IF(AND(B58="Question",M58=""),"Sévérité manquante","OK")))))) | L58: =", "&J58&"," | M58: Mineur | N58: Test de sauvegarde du logiciel documentaire
A59: 58 | B59: Question | D59: Q047 | E59: Q046 | G59: Q007 | H59: OUI | I59: Les documents existent sous forme électronique et/ou papier | J59: 4.06 | K59: =IF(COUNTIF($D$2:$D$2000,D59)>1,"Code en double",IF(AND(F59<>"",COUNTIF($D$2:$D$2000,F59)=0),"Question chapeau inconnue",IF(AND(G59<>"",COUNTIF($D$2:$D$2000,G59)=0),"Condition inconnue",IF(G59=D59,"Dépend d'elle-même",IF(J59="","Aucune réf. BPP",IF(AND(B59="Question",M59=""),"Sévérité manquante","OK")))))) | L59: =", "&J59&"," | M59: Mineur | N59: Support des documents
A60: 59 | B60: Question | D60: Q048 | E60: Q047 | I60: Il existe un logiciel pour la réalisation des préparations | J60: 4.03 | K60: =IF(COUNTIF($D$2:$D$2000,D60)>1,"Code en double",IF(AND(F60<>"",COUNTIF($D$2:$D$2000,F60)=0),"Question chapeau inconnue",IF(AND(G60<>"",COUNTIF($D$2:$D$2000,G60)=0),"Condition inconnue",IF(G60=D60,"Dépend d'elle-même",IF(J60="","Aucune réf. BPP",IF(AND(B60="Question",M60=""),"Sévérité manquante","OK")))))) | L60: =", "&J60&"," | M60: Mineur | N60: Outil logiciel de préparation
A61: 60 | B61: Titre | C61: 2 | I61: GÉNÉRALITÉS ET BONNES PRATIQUES DOCUMENTAIRES
A62: 61 | B62: Question | D62: Q049 | E62: Q048 | G62: Q007 | H62: OUI | I62: Il existe une procédure de gestion documentaire | J62: 4.04 | K62: =IF(COUNTIF($D$2:$D$2000,D62)>1,"Code en double",IF(AND(F62<>"",COUNTIF($D$2:$D$2000,F62)=0),"Question chapeau inconnue",IF(AND(G62<>"",COUNTIF($D$2:$D$2000,G62)=0),"Condition inconnue",IF(G62=D62,"Dépend d'elle-même",IF(J62="","Aucune réf. BPP",IF(AND(B62="Question",M62=""),"Sévérité manquante","OK")))))) | L62: =", "&J62&"," | M62: Majeur | N62: Procédure de gestion documentaire
A63: 62 | B63: Question | D63: Q050 | E63: Q049 | G63: Q049 | H63: OUI | I63: La procédure de gestion documentaire couvre explicitement le cycle de vie complet (création, validation, diffusion, révision, archivage, destruction) de chaque type de document | J63: 4.04 | K63: =IF(COUNTIF($D$2:$D$2000,D63)>1,"Code en double",IF(AND(F63<>"",COUNTIF($D$2:$D$2000,F63)=0),"Question chapeau inconnue",IF(AND(G63<>"",COUNTIF($D$2:$D$2000,G63)=0),"Condition inconnue",IF(G63=D63,"Dépend d'elle-même",IF(J63="","Aucune réf. BPP",IF(AND(B63="Question",M63=""),"Sévérité manquante","OK")))))) | L63: =", "&J63&"," | M63: Mineur | N63: Détail du cycle de vie documentaire
A64: 63 | B64: Question | D64: Q051 | E64: Q050 | G64: Q049 | H64: OUI | I64: La procédure de gestion documentaire prévoit la mise à jour et la diffusion des documents en prenant en compte les risques liés à la reproduction des documents qualité | J64: 4.07 | K64: =IF(COUNTIF($D$2:$D$2000,D64)>1,"Code en double",IF(AND(F64<>"",COUNTIF($D$2:$D$2000,F64)=0),"Question chapeau inconnue",IF(AND(G64<>"",COUNTIF($D$2:$D$2000,G64)=0),"Condition inconnue",IF(G64=D64,"Dépend d'elle-même",IF(J64="","Aucune réf. BPP",IF(AND(B64="Question",M64=""),"Sévérité manquante","OK")))))) | L64: =", "&J64&"," | M64: Mineur | N64: Maîtrise des copies de documents
A65: 64 | B65: Intitulé commun | D65: Q052 | E65: Q051 | G65: Q049 | H65: OUI | I65: La procédure des gestion documentaitre précise le circuit de validation des documents qui sont | J65: 4.08 | K65: =IF(COUNTIF($D$2:$D$2000,D65)>1,"Code en double",IF(AND(F65<>"",COUNTIF($D$2:$D$2000,F65)=0),"Question chapeau inconnue",IF(AND(G65<>"",COUNTIF($D$2:$D$2000,G65)=0),"Condition inconnue",IF(G65=D65,"Dépend d'elle-même",IF(J65="","Aucune réf. BPP",IF(AND(B65="Question",M65=""),"Sévérité manquante","OK")))))) | L65: =", "&J65&","
A66: 65 | B66: Question | D66: Q052.01 | E66: Q051.01 | F66: Q052 | G66: Q049 | H66: OUI | I66: rédigés par une personne identifiée et autorisée | J66: 4.08 | K66: =IF(COUNTIF($D$2:$D$2000,D66)>1,"Code en double",IF(AND(F66<>"",COUNTIF($D$2:$D$2000,F66)=0),"Question chapeau inconnue",IF(AND(G66<>"",COUNTIF($D$2:$D$2000,G66)=0),"Condition inconnue",IF(G66=D66,"Dépend d'elle-même",IF(J66="","Aucune réf. BPP",IF(AND(B66="Question",M66=""),"Sévérité manquante","OK")))))) | L66: =", "&J66&"," | M66: Mineur | N66: Identification du rédacteur
A67: 66 | B67: Question | D67: Q052.02 | E67: Q051.02 | F67: Q052 | G67: Q049 | H67: OUI | I67: vérifiés par une personne identifiée et autorisée | J67: 4.08 | K67: =IF(COUNTIF($D$2:$D$2000,D67)>1,"Code en double",IF(AND(F67<>"",COUNTIF($D$2:$D$2000,F67)=0),"Question chapeau inconnue",IF(AND(G67<>"",COUNTIF($D$2:$D$2000,G67)=0),"Condition inconnue",IF(G67=D67,"Dépend d'elle-même",IF(J67="","Aucune réf. BPP",IF(AND(B67="Question",M67=""),"Sévérité manquante","OK")))))) | L67: =", "&J67&"," | M67: Mineur | N67: Identification du vérificateur
A68: 67 | B68: Question | D68: Q052.03 | E68: Q051.03 | F68: Q052 | G68: Q049 | H68: OUI | I68: approuvés par une personne identifiée et autorisée | J68: 4.08 | K68: =IF(COUNTIF($D$2:$D$2000,D68)>1,"Code en double",IF(AND(F68<>"",COUNTIF($D$2:$D$2000,F68)=0),"Question chapeau inconnue",IF(AND(G68<>"",COUNTIF($D$2:$D$2000,G68)=0),"Condition inconnue",IF(G68=D68,"Dépend d'elle-même",IF(J68="","Aucune réf. BPP",IF(AND(B68="Question",M68=""),"Sévérité manquante","OK")))))) | L68: =", "&J68&"," | M68: Mineur | N68: Identification de l'approbateur
A69: 68 | B69: Question | D69: Q053 | E69: Q052 | G69: Q049 | H69: OUI | I69: La procédure de gestion documentaire prévoit une révision régulière des documents | J69: 4.10 | K69: =IF(COUNTIF($D$2:$D$2000,D69)>1,"Code en double",IF(AND(F69<>"",COUNTIF($D$2:$D$2000,F69)=0),"Question chapeau inconnue",IF(AND(G69<>"",COUNTIF($D$2:$D$2000,G69)=0),"Condition inconnue",IF(G69=D69,"Dépend d'elle-même",IF(J69="","Aucune réf. BPP",IF(AND(B69="Question",M69=""),"Sévérité manquante","OK")))))) | L69: =", "&J69&"," | M69: Mineur | N69: Révision régulière des documents
A70: 69 | B70: Question | D70: Q054 | E70: Q053 | G70: Q007 | H70: OUI | I70: Les procédures validées sont diffusées spécifiquement aux personnels concernées (logiciel de gestion documentaire, diffusion papier, réunion de service avec compte rendu…) | J70: 2.04 | K70: =IF(COUNTIF($D$2:$D$2000,D70)>1,"Code en double",IF(AND(F70<>"",COUNTIF($D$2:$D$2000,F70)=0),"Question chapeau inconnue",IF(AND(G70<>"",COUNTIF($D$2:$D$2000,G70)=0),"Condition inconnue",IF(G70=D70,"Dépend d'elle-même",IF(J70="","Aucune réf. BPP",IF(AND(B70="Question",M70=""),"Sévérité manquante","OK")))))) | L70: =", "&J70&"," | M70: Mineur | N70: Modalités de diffusion des procédures
A71: 70 | B71: Question | D71: Q055 | E71: Q054 | G71: Q007 | H71: OUI | I71: Le personnel a accès à la documentation relative à son activité | J71: 4.04, 2.01, 2.04, 6.29 | K71: =IF(COUNTIF($D$2:$D$2000,D71)>1,"Code en double",IF(AND(F71<>"",COUNTIF($D$2:$D$2000,F71)=0),"Question chapeau inconnue",IF(AND(G71<>"",COUNTIF($D$2:$D$2000,G71)=0),"Condition inconnue",IF(G71=D71,"Dépend d'elle-même",IF(J71="","Aucune réf. BPP",IF(AND(B71="Question",M71=""),"Sévérité manquante","OK")))))) | L71: =", "&J71&"," | M71: Majeur | N71: Accès du personnel à sa documentation
A72: 71 | B72: Question | D72: Q056 | E72: Q055 | G72: Q007 | H72: OUI | I72: Le mode de diffusion des documents garantit une preuve de prise de connaissance individuelle par chaque membre du personnel concerné | J72: 4.04, 2.01 | K72: =IF(COUNTIF($D$2:$D$2000,D72)>1,"Code en double",IF(AND(F72<>"",COUNTIF($D$2:$D$2000,F72)=0),"Question chapeau inconnue",IF(AND(G72<>"",COUNTIF($D$2:$D$2000,G72)=0),"Condition inconnue",IF(G72=D72,"Dépend d'elle-même",IF(J72="","Aucune réf. BPP",IF(AND(B72="Question",M72=""),"Sévérité manquante","OK")))))) | L72: =", "&J72&"," | M72: Mineur | N72: Preuve de prise de connaissance individuelle
A73: 72 | B73: Question | D73: Q057 | E73: Q056 | G73: Q007 | H73: OUI | I73: Les procédures applicables dans la ZAC sont communiquées est connue des personnes étrangères à la PUI autorisées par le PRP / gérant PUI à entrer dans les zones de préparation, de contrôle et de stockage | J73: LD1.116, 3.05 | K73: =IF(COUNTIF($D$2:$D$2000,D73)>1,"Code en double",IF(AND(F73<>"",COUNTIF($D$2:$D$2000,F73)=0),"Question chapeau inconnue",IF(AND(G73<>"",COUNTIF($D$2:$D$2000,G73)=0),"Condition inconnue",IF(G73=D73,"Dépend d'elle-même",IF(J73="","Aucune réf. BPP",IF(AND(B73="Question",M73=""),"Sévérité manquante","OK")))))) | L73: =", "&J73&"," | M73: Majeur | N73: Procédures ZAC connues des intervenants extérieurs
A74: 73 | B74: Question | D74: Q058 | E74: Q057 | I74: Il existe système de déclaration/documentation relative aux écarts qualité des produits | J74: 4.05 | K74: =IF(COUNTIF($D$2:$D$2000,D74)>1,"Code en double",IF(AND(F74<>"",COUNTIF($D$2:$D$2000,F74)=0),"Question chapeau inconnue",IF(AND(G74<>"",COUNTIF($D$2:$D$2000,G74)=0),"Condition inconnue",IF(G74=D74,"Dépend d'elle-même",IF(J74="","Aucune réf. BPP",IF(AND(B74="Question",M74=""),"Sévérité manquante","OK")))))) | L74: =", "&J74&"," | M74: Majeur | N74: Système de déclaration des écarts qualité
A75: 74 | B75: Question | D75: Q059 | E75: Q058 | G75: Q058 | H75: OUI | I75: Le système de déclaration /documentation relative aux écarts de qualité des produits est utilisé en pratique (ex : nombre de déclarations sur les 12 derniers mois) | J75: 4.05 | K75: =IF(COUNTIF($D$2:$D$2000,D75)>1,"Code en double",IF(AND(F75<>"",COUNTIF($D$2:$D$2000,F75)=0),"Question chapeau inconnue",IF(AND(G75<>"",COUNTIF($D$2:$D$2000,G75)=0),"Condition inconnue",IF(G75=D75,"Dépend d'elle-même",IF(J75="","Aucune réf. BPP",IF(AND(B75="Question",M75=""),"Sévérité manquante","OK")))))) | L75: =", "&J75&"," | M75: Majeur | N75: Utilisation effective de la déclaration des écarts
A76: 75 | B76: Question | D76: Q060 | E76: Q059 | G76: Q007 | H76: OUI | I76: Des contrôles des enregistrements (durée d'utilisation et archivage) sont réalisés | J76: 4.06 | K76: =IF(COUNTIF($D$2:$D$2000,D76)>1,"Code en double",IF(AND(F76<>"",COUNTIF($D$2:$D$2000,F76)=0),"Question chapeau inconnue",IF(AND(G76<>"",COUNTIF($D$2:$D$2000,G76)=0),"Condition inconnue",IF(G76=D76,"Dépend d'elle-même",IF(J76="","Aucune réf. BPP",IF(AND(B76="Question",M76=""),"Sévérité manquante","OK")))))) | L76: =", "&J76&"," | M76: Mineur | N76: Contrôle des enregistrements et archivage
A77: 76 | B77: Question | D77: Q061 | E77: Q060 | G77: Q007 | H77: OUI | I77: La date de rédaction du document qualité est enregistrée | J77: 4.08 | K77: =IF(COUNTIF($D$2:$D$2000,D77)>1,"Code en double",IF(AND(F77<>"",COUNTIF($D$2:$D$2000,F77)=0),"Question chapeau inconnue",IF(AND(G77<>"",COUNTIF($D$2:$D$2000,G77)=0),"Condition inconnue",IF(G77=D77,"Dépend d'elle-même",IF(J77="","Aucune réf. BPP",IF(AND(B77="Question",M77=""),"Sévérité manquante","OK")))))) | L77: =", "&J77&"," | M77: Mineur | N77: Date de rédaction des documents
A78: 77 | B78: Question | D78: Q062 | E78: Q061 | G78: Q007 | H78: OUI | I78: La date de mise en application du document qualité est enregistrée | J78: 4.08 | K78: =IF(COUNTIF($D$2:$D$2000,D78)>1,"Code en double",IF(AND(F78<>"",COUNTIF($D$2:$D$2000,F78)=0),"Question chapeau inconnue",IF(AND(G78<>"",COUNTIF($D$2:$D$2000,G78)=0),"Condition inconnue",IF(G78=D78,"Dépend d'elle-même",IF(J78="","Aucune réf. BPP",IF(AND(B78="Question",M78=""),"Sévérité manquante","OK")))))) | L78: =", "&J78&"," | M78: Mineur | N78: Date d'application des documents
A79: 78 | B79: Question | D79: Q063 | E79: Q062 | G79: Q007 | H79: OUI | I79: Les documents sont présentées de façon ordonnées (codification prévue dans la procedure de gestion documentaire) | J79: 4.09 | K79: =IF(COUNTIF($D$2:$D$2000,D79)>1,"Code en double",IF(AND(F79<>"",COUNTIF($D$2:$D$2000,F79)=0),"Question chapeau inconnue",IF(AND(G79<>"",COUNTIF($D$2:$D$2000,G79)=0),"Condition inconnue",IF(G79=D79,"Dépend d'elle-même",IF(J79="","Aucune réf. BPP",IF(AND(B79="Question",M79=""),"Sévérité manquante","OK")))))) | L79: =", "&J79&"," | M79: Mineur | N79: Codification des documents
A80: 79 | B80: Question | D80: Q064 | E80: Q063 | G80: Q007 | H80: OUI | I80: Le style directif est obligatoirement utilisé pour les procédures, les instructions de travail et les modes opératoires | J80: 4.09 | K80: =IF(COUNTIF($D$2:$D$2000,D80)>1,"Code en double",IF(AND(F80<>"",COUNTIF($D$2:$D$2000,F80)=0),"Question chapeau inconnue",IF(AND(G80<>"",COUNTIF($D$2:$D$2000,G80)=0),"Condition inconnue",IF(G80=D80,"Dépend d'elle-même",IF(J80="","Aucune réf. BPP",IF(AND(B80="Question",M80=""),"Sévérité manquante","OK")))))) | L80: =", "&J80&"," | M80: Mineur | N80: Style rédactionnel des procédures
A81: 80 | B81: Question | D81: Q065 | E81: Q064 | G81: Q007 | H81: OUI | I81: La périodicité de révision des documents qualité est définie par type de document, avec une alerte automatique ou un suivi des échéances de révision dépassées | J81: 4.10 | K81: =IF(COUNTIF($D$2:$D$2000,D81)>1,"Code en double",IF(AND(F81<>"",COUNTIF($D$2:$D$2000,F81)=0),"Question chapeau inconnue",IF(AND(G81<>"",COUNTIF($D$2:$D$2000,G81)=0),"Condition inconnue",IF(G81=D81,"Dépend d'elle-même",IF(J81="","Aucune réf. BPP",IF(AND(B81="Question",M81=""),"Sévérité manquante","OK")))))) | L81: =", "&J81&"," | M81: Mineur | N81: Périodicité et suivi des révisions
A82: 81 | B82: Intitulé commun | D82: Q066 | E82: Q065 | G82: Q007 | H82: OUI | I82: En cas de documentation papier, les documents sont : | J82: 4.02 | K82: =IF(COUNTIF($D$2:$D$2000,D82)>1,"Code en double",IF(AND(F82<>"",COUNTIF($D$2:$D$2000,F82)=0),"Question chapeau inconnue",IF(AND(G82<>"",COUNTIF($D$2:$D$2000,G82)=0),"Condition inconnue",IF(G82=D82,"Dépend d'elle-même",IF(J82="","Aucune réf. BPP",IF(AND(B82="Question",M82=""),"Sévérité manquante","OK")))))) | L82: =", "&J82&","
A83: 82 | B83: Question | D83: Q066.01 | E83: Q065.01 | F83: Q066 | G83: Q007 | H83: OUI | I83: Dactylographiés | J83: 4.02 | K83: =IF(COUNTIF($D$2:$D$2000,D83)>1,"Code en double",IF(AND(F83<>"",COUNTIF($D$2:$D$2000,F83)=0),"Question chapeau inconnue",IF(AND(G83<>"",COUNTIF($D$2:$D$2000,G83)=0),"Condition inconnue",IF(G83=D83,"Dépend d'elle-même",IF(J83="","Aucune réf. BPP",IF(AND(B83="Question",M83=""),"Sévérité manquante","OK")))))) | L83: =", "&J83&"," | M83: Mineur | N83: Forme dactylographiée des documents
A84: 83 | B84: Question | D84: Q066.02 | E84: Q065.02 | F84: Q066 | G84: Q007 | H84: OUI | I84: Avec de rares entrées manuscrites validées | J84: 4.02 | K84: =IF(COUNTIF($D$2:$D$2000,D84)>1,"Code en double",IF(AND(F84<>"",COUNTIF($D$2:$D$2000,F84)=0),"Question chapeau inconnue",IF(AND(G84<>"",COUNTIF($D$2:$D$2000,G84)=0),"Condition inconnue",IF(G84=D84,"Dépend d'elle-même",IF(J84="","Aucune réf. BPP",IF(AND(B84="Question",M84=""),"Sévérité manquante","OK")))))) | L84: =", "&J84&"," | M84: Mineur | N84: Limitation des entrées manuscrites
A85: 84 | B85: Question | D85: Q067 | E85: Q066 | G85: Q007 | H85: OUI | I85: Les enregistrements manuscrits sont limités. | J85: 4.11 | K85: =IF(COUNTIF($D$2:$D$2000,D85)>1,"Code en double",IF(AND(F85<>"",COUNTIF($D$2:$D$2000,F85)=0),"Question chapeau inconnue",IF(AND(G85<>"",COUNTIF($D$2:$D$2000,G85)=0),"Condition inconnue",IF(G85=D85,"Dépend d'elle-même",IF(J85="","Aucune réf. BPP",IF(AND(B85="Question",M85=""),"Sévérité manquante","OK")))))) | L85: =", "&J85&"," | M85: Mineur | N85: Limitation des enregistrements manuscrits
A86: 85 | B86: Question | D86: Q067.01 | E86: Q066.01 | F86: Q067 | G86: Q007 | H86: OUI | I86: Ils sont lisibles | J86: 4.11 | K86: =IF(COUNTIF($D$2:$D$2000,D86)>1,"Code en double",IF(AND(F86<>"",COUNTIF($D$2:$D$2000,F86)=0),"Question chapeau inconnue",IF(AND(G86<>"",COUNTIF($D$2:$D$2000,G86)=0),"Condition inconnue",IF(G86=D86,"Dépend d'elle-même",IF(J86="","Aucune réf. BPP",IF(AND(B86="Question",M86=""),"Sévérité manquante","OK")))))) | L86: =", "&J86&"," | M86: Majeur | N86: Lisibilité des enregistrements, risque d'erreur
A87: 86 | B87: Question | D87: Q067.02 | E87: Q066.02 | F87: Q067 | G87: Q007 | H87: OUI | I87: Ils sont indélébiles | J87: 4.11 | K87: =IF(COUNTIF($D$2:$D$2000,D87)>1,"Code en double",IF(AND(F87<>"",COUNTIF($D$2:$D$2000,F87)=0),"Question chapeau inconnue",IF(AND(G87<>"",COUNTIF($D$2:$D$2000,G87)=0),"Condition inconnue",IF(G87=D87,"Dépend d'elle-même",IF(J87="","Aucune réf. BPP",IF(AND(B87="Question",M87=""),"Sévérité manquante","OK")))))) | L87: =", "&J87&"," | M87: Majeur | N87: Enregistrements indélébiles, intégrité des données
A88: 87 | B88: Question | D88: Q067.03 | E88: Q066.03 | F88: Q067 | G88: Q007 | H88: OUI | I88: Leur auteur est identifié | J88: 4.11 | K88: =IF(COUNTIF($D$2:$D$2000,D88)>1,"Code en double",IF(AND(F88<>"",COUNTIF($D$2:$D$2000,F88)=0),"Question chapeau inconnue",IF(AND(G88<>"",COUNTIF($D$2:$D$2000,G88)=0),"Condition inconnue",IF(G88=D88,"Dépend d'elle-même",IF(J88="","Aucune réf. BPP",IF(AND(B88="Question",M88=""),"Sévérité manquante","OK")))))) | L88: =", "&J88&"," | M88: Majeur | N88: Identification de l'auteur, traçabilité
A89: 88 | B89: Question | D89: Q067.04 | E89: Q066.04 | F89: Q067 | G89: Q007 | H89: OUI | I89: Leur date/horaire de rédaction est tracé | J89: 4.11 | K89: =IF(COUNTIF($D$2:$D$2000,D89)>1,"Code en double",IF(AND(F89<>"",COUNTIF($D$2:$D$2000,F89)=0),"Question chapeau inconnue",IF(AND(G89<>"",COUNTIF($D$2:$D$2000,G89)=0),"Condition inconnue",IF(G89=D89,"Dépend d'elle-même",IF(J89="","Aucune réf. BPP",IF(AND(B89="Question",M89=""),"Sévérité manquante","OK")))))) | L89: =", "&J89&"," | M89: Majeur | N89: Horodatage des enregistrements, traçabilité
A90: 89 | B90: Question | D90: Q068 | E90: Q067 | G90: Q007 | H90: OUI | I90: Il existe des procédures générales | J90: 4.12, 1.07 | K90: =IF(COUNTIF($D$2:$D$2000,D90)>1,"Code en double",IF(AND(F90<>"",COUNTIF($D$2:$D$2000,F90)=0),"Question chapeau inconnue",IF(AND(G90<>"",COUNTIF($D$2:$D$2000,G90)=0),"Condition inconnue",IF(G90=D90,"Dépend d'elle-même",IF(J90="","Aucune réf. BPP",IF(AND(B90="Question",M90=""),"Sévérité manquante","OK")))))) | L90: =", "&J90&"," | M90: Majeur | N90: Existence des procédures générales
A91: 90 | B91: Question | D91: Q069 | E91: Q068 | G91: Q007 | H91: OUI | I91: Il existe des dossiers de préparation (modes opératoires, fiches de fabrication) | J91: 4.12, 1.07, 5.01, 5.06 | K91: =IF(COUNTIF($D$2:$D$2000,D91)>1,"Code en double",IF(AND(F91<>"",COUNTIF($D$2:$D$2000,F91)=0),"Question chapeau inconnue",IF(AND(G91<>"",COUNTIF($D$2:$D$2000,G91)=0),"Condition inconnue",IF(G91=D91,"Dépend d'elle-même",IF(J91="","Aucune réf. BPP",IF(AND(B91="Question",M91=""),"Sévérité manquante","OK")))))) | L91: =", "&J91&"," | M91: Majeur | N91: Dossiers de préparation et modes opératoires
A92: 91 | B92: Question | D92: Q070 | E92: Q069 | G92: Q007 | H92: OUI | I92: Un dossier de prépration est réalisé pour chaque type de préparation ; il reprend la validité technico réglementaire, et comprend : la préparation et son procédé, les spécifications, contrôles et éléments d'assurance qualité (annexe II parties 1,2,3) | J92: 1.14, 1.18, 4.30, 5.01 | K92: =IF(COUNTIF($D$2:$D$2000,D92)>1,"Code en double",IF(AND(F92<>"",COUNTIF($D$2:$D$2000,F92)=0),"Question chapeau inconnue",IF(AND(G92<>"",COUNTIF($D$2:$D$2000,G92)=0),"Condition inconnue",IF(G92=D92,"Dépend d'elle-même",IF(J92="","Aucune réf. BPP",IF(AND(B92="Question",M92=""),"Sévérité manquante","OK")))))) | L92: =", "&J92&"," | M92: Majeur | N92: Contenu du dossier de préparation
A93: 92 | B93: Question | D93: Q071 | E93: Q070 | G93: Q007 | H93: OUI | I93: Un dossier de préparation est réalisé pour plusieurs préparations de même composition qualitative quand les procédés de préparation et les méthodes de contrôle sont identiques | J93: 4.31 | K93: =IF(COUNTIF($D$2:$D$2000,D93)>1,"Code en double",IF(AND(F93<>"",COUNTIF($D$2:$D$2000,F93)=0),"Question chapeau inconnue",IF(AND(G93<>"",COUNTIF($D$2:$D$2000,G93)=0),"Condition inconnue",IF(G93=D93,"Dépend d'elle-même",IF(J93="","Aucune réf. BPP",IF(AND(B93="Question",M93=""),"Sévérité manquante","OK")))))) | L93: =", "&J93&"," | M93: Mineur | N93: Regroupement des dossiers de préparation
A94: 93 | B94: Question | D94: Q072 | E94: Q071 | G94: Q007 | H94: OUI | I94: Il existe des dossiers de lot (enregistrements) | J94: 4.12, 1.07, LD1.145 | K94: =IF(COUNTIF($D$2:$D$2000,D94)>1,"Code en double",IF(AND(F94<>"",COUNTIF($D$2:$D$2000,F94)=0),"Question chapeau inconnue",IF(AND(G94<>"",COUNTIF($D$2:$D$2000,G94)=0),"Condition inconnue",IF(G94=D94,"Dépend d'elle-même",IF(J94="","Aucune réf. BPP",IF(AND(B94="Question",M94=""),"Sévérité manquante","OK")))))) | L94: =", "&J94&"," | M94: Majeur | N94: Dossiers de lot, traçabilité des préparations
A95: 94 | B95: Titre | C95: 2 | I95: PROCÉDURES GÉNÉRALES
A96: 95 | B96: Question | D96: Q073 | E96: Q072 | G96: Q007 | H96: OUI | I96: Il existe une (des) procédure(s) relative(s) aux opérations de préparation | J96: 1.05, 4.13, 5.01 | K96: =IF(COUNTIF($D$2:$D$2000,D96)>1,"Code en double",IF(AND(F96<>"",COUNTIF($D$2:$D$2000,F96)=0),"Question chapeau inconnue",IF(AND(G96<>"",COUNTIF($D$2:$D$2000,G96)=0),"Condition inconnue",IF(G96=D96,"Dépend d'elle-même",IF(J96="","Aucune réf. BPP",IF(AND(B96="Question",M96=""),"Sévérité manquante","OK")))))) | L96: =", "&J96&"," | M96: Majeur | N96: Procédure des opérations de préparation
A97: 96 | B97: Intitulé commun | D97: Q074 | E97: Q073 | G97: Q073 | H97: OUI | I97: La(les) procédure(s) relative(s) aux opérations de préparation précise(nt) qu'il est nécessaire de | J97: 5.34 | K97: =IF(COUNTIF($D$2:$D$2000,D97)>1,"Code en double",IF(AND(F97<>"",COUNTIF($D$2:$D$2000,F97)=0),"Question chapeau inconnue",IF(AND(G97<>"",COUNTIF($D$2:$D$2000,G97)=0),"Condition inconnue",IF(G97=D97,"Dépend d'elle-même",IF(J97="","Aucune réf. BPP",IF(AND(B97="Question",M97=""),"Sévérité manquante","OK")))))) | L97: =", "&J97&","
A98: 97 | B98: Question | D98: Q074.01 | E98: Q073.01 | F98: Q074 | G98: Q073 | H98: OUI | I98: ne réaliser qu’une seule préparation à la fois, sur une même zone de travail, afin d’éviter les risques d’erreurs et de contaminations croisées | J98: 5.34 | K98: =IF(COUNTIF($D$2:$D$2000,D98)>1,"Code en double",IF(AND(F98<>"",COUNTIF($D$2:$D$2000,F98)=0),"Question chapeau inconnue",IF(AND(G98<>"",COUNTIF($D$2:$D$2000,G98)=0),"Condition inconnue",IF(G98=D98,"Dépend d'elle-même",IF(J98="","Aucune réf. BPP",IF(AND(B98="Question",M98=""),"Sévérité manquante","OK")))))) | L98: =", "&J98&"," | M98: Critique | N98: Une préparation à la fois : prévient confusions et contaminations croisées
A99: 98 | B99: Question | D99: Q074.02 | E99: Q073.02 | F99: Q074 | G99: Q073 | H99: OUI | I99: confier préférentiellement à la même personne qualifiée au sens du CSP la totalité des opérations d’un lot de préparation | J99: 5.34 | K99: =IF(COUNTIF($D$2:$D$2000,D99)>1,"Code en double",IF(AND(F99<>"",COUNTIF($D$2:$D$2000,F99)=0),"Question chapeau inconnue",IF(AND(G99<>"",COUNTIF($D$2:$D$2000,G99)=0),"Condition inconnue",IF(G99=D99,"Dépend d'elle-même",IF(J99="","Aucune réf. BPP",IF(AND(B99="Question",M99=""),"Sévérité manquante","OK")))))) | L99: =", "&J99&"," | M99: Mineur | N99: Même opérateur pour tout le lot, préférentiel
A100: 99 | B100: Question | D100: Q074.03 | E100: Q073.03 | F100: Q074 | G100: Q073 | H100: OUI | I100: ne pas interrompre cette personne avant la réalisation complète de la préparation | J100: 5.34 | K100: =IF(COUNTIF($D$2:$D$2000,D100)>1,"Code en double",IF(AND(F100<>"",COUNTIF($D$2:$D$2000,F100)=0),"Question chapeau inconnue",IF(AND(G100<>"",COUNTIF($D$2:$D$2000,G100)=0),"Condition inconnue",IF(G100=D100,"Dépend d'elle-même",IF(J100="","Aucune réf. BPP",IF(AND(B100="Question",M100=""),"Sévérité manquante","OK")))))) | L100: =", "&J100&"," | M100: Majeur | N100: Interruption de l'opérateur, source d'erreurs
...

Sheet Sévérités
A1: Répartition des sévérités
A3: Niveau | B3: Nombre de questions
A4: Critique | B4: =COUNTIF('Référentiel'!$M:$M,A4)
A5: Majeur | B5: =COUNTIF('Référentiel'!$M:$M,A5)
A6: Mineur | B6: =COUNTIF('Référentiel'!$M:$M,A6)
A7: Total | B7: =SUM(B4:B6)
A9: Pondération appliquée selon la réponse (dans l'outil questionnaire)
A11: Réponse | B11: Poids | C11: Justification
A12: Conforme | B12: 0 | C12: Confirmé conforme : aucun risque retenu.
A13: Partiellement conforme | B13: 0.5 | C13: Écart confirmé mais partiel.
A14: Non applicable | B14: 0 | C14: Neutre, comme Conforme : ne contribue pas au verdict de risque.
A15: Non conforme | B15: 1 | C15: Écart confirmé et total : poids plein.
A17: Verdict d'un chapitre = sévérité la plus élevée parmi les écarts pondérés (poids > 0) qu'il contient. Un seul écart Critique confirmé (Non conforme, poids 1) suffit à classer tout le chapitre en risque critique ; un écart Critique seulement partiel (poids 0,5) le fait basculer en risque majeur, un écart Majeur partiel en risque mineur. Le Non applicable n'a pas d'effet sur ce calcul. Lorsqu'une question maître est répondue « Non » (ou « N/A »), les questions qui en dépendent sont réputées « Non » (ou « N/A »).

Sheet Références BPP
A1: Réf. BPP | B1: Texte officiel | C1: Nb de questions
A2: 1.01 | B2: Afin de protéger la santé humaine, les préparations pharmaceutiques sont réalisées de façon à garantir une qualité constante, appropriée à leur usage. Pour atteindre cet objectif elles sont réalisées en conformité avec les exigences définies dans le présent texte. | C2: =COUNTIF(Référentiel!$L$2:$L$1371,"*, "&A2&",*")
A3: 1.02 | B3: Les pharmacies à usage intérieur et les pharmacies d'officine disposent d’un système d’assurance qualité qui intègre l’ensemble des règles de bonnes pratiques présentées dans ce texte. Ce système est documenté et contrôlé et son efficacité est surveillée. | C3: =COUNTIF(Référentiel!$L$2:$L$1371,"*, "&A3&",*")
A4: 1.03 | B4: Les concepts fondamentaux de la gestion de la qualité, des Bonnes Pratiques de Préparation (BPP) et de la gestion du risque sont étroitement liés. Ils sont décrits ci-après en vue de souligner leurs relations réciproques et leur importance fondamentale dans la production et le contrôle des préparations pharmaceutiques. | C4: =COUNTIF(Référentiel!$L$2:$L$1371,"*, "&A4&",*")
A5: 1.04 | B5: La gestion de la qualité est un concept large qui couvre tout ce qui peut, individuellement ou collectivement, avoir une influence sur la qualité d’un produit. Elle représente l’ensemble des dispositions prises pour garantir que les préparations sont conformes aux spécifications attendues et de qualité requise pour l’usage auquel elles sont destinées. La gestion de la qualité intègre les BPP. | C5: =COUNTIF(Référentiel!$L$2:$L$1371,"*, "&A5&",*")
A6: 1.05 | B6: Le système d’assurance qualité est soumis à une évaluation de son efficacité et de son adéquation entre le présent texte et les pratiques mises en oeuvre : -un système documentaire est mis en place et maîtrisé ; -les préparations sont formulées et réalisées selon l’état des connaissances scientifiques, médicales et pharmaceutiques ; -les procédés de préparation et de contrôle sont clairement décrits et les règles figurant dans le présent texte sont appliquées ; -une fois réalisées, les préparations n’entrent dans le circuit de dispensation qu’une fois contrôlées et libérées conformément aux procédures établies ; -des dispositions sont prises pour garantir la qualité des préparations jusqu’à leur date de péremption et leur délai limite d’utilisation après ouverture. | C6: =COUNTIF(Référentiel!$L$2:$L$1371,"*, "&A6&",*")
A7: 1.06 | B7: Les BPP constituent un des éléments de la gestion de la qualité qui garantit que les préparations pharmaceutiques sont réalisées et contrôlées de façon cohérente, selon leurs spécifications et les normes de qualité adaptées à leur usage. | C7: =COUNTIF(Référentiel!$L$2:$L$1371,"*, "&A7&",*")
A8: 1.07 | B8: Les BPP s’appliquent à la fois à la production et au contrôle de la qualité des préparations pharmaceutiques. Les exigences fondamentales des BPP sont les suivantes : -le personnel est qualifié et formé à la fonction qu’il occupe. Les responsabilités et les compétences sont clairement définies ; -les locaux et équipements sont adaptés aux préparations à réaliser ; -tous les facteurs influençant la qualité des préparations sont évalués et sont décrits dans des documents appropriés ; -tout procédé de préparation respecte le présent texte. Toutes les étapes requises par les procédures sont documentées. Les dossiers de lot sont établis de manière à permettre la traçabilité complète du lot de la préparation concernée jusqu’à sa libération et sa dispensation aux patients, en tenant compte des dispositions décrites au chapitre 7 dans le cas où l’activité est externalisée ; -la manipulation, le transport et le stockage des matières premières à usage pharmaceutique (MPUP) et des articles de conditionnement se déroulent de façon à garantir leur qualité pendant toute leur durée de validité ; -la qualité des produits obtenus est évaluée et satisfait aux exigences requises ; l’évaluation est documentée et inclut : *un examen des documents de préparation ; *la réalisation de contrôles qualité ; * une comparaison entre les résultats des contrôles qualité et les spécifications exigées ; *une analyse des écarts éventuels. -les lots ne sont libérés qu’après vérification et attestation de leur conformité aux spécifications requises ; -les réclamations et les non-conformités concernant les préparations pharmaceutiques, les MPUP et les articles de conditionnement sont examinées et étudiées afin de prendre les mesures correctives adaptées. | C8: =COUNTIF(Référentiel!$L$2:$L$1371,"*, "&A8&",*")
A9: 1.08 | B9: Le contrôle de la qualité fait partie des BPP (cf. Chapitre 6). Il concerne l’échantillonnage, les spécifications et le contrôle, ainsi que les procédures d’organisation, de documentation et de libération qui garantissent que les contrôles qualité nécessaires et appropriés sont réellement effectués. Les MPUP, les articles de conditionnement, les produits intermédiaires, les préparations utilisées pour la réalisation d’autres préparations et les préparations terminées ne sont libérées qu’après vérification de leur qualité et de leur conformité aux spécifications. | C9: =COUNTIF(Référentiel!$L$2:$L$1371,"*, "&A9&",*")
A10: 1.09 | B10: La nature du contrôle de la qualité est définie et justifiée en fonction de l'analyse de risque réalisée pour la préparation concernée. | C10: =COUNTIF(Référentiel!$L$2:$L$1371,"*, "&A10&",*")
A11: 1.10 | B11: Après analyse des réclamations et des non-conformités, il est recommandé de réaliser des revues qualités portant notamment sur les préparations pour lesquelles un écart ou une modification substantielle a été relevée. Ces revues sont menées afin de vérifier la répétabilité des procédés existants, la pertinence des spécifications initialement décrites dans le dossier de préparation (cf. Annexe II) pour les MPUP, les articles de conditionnement, les produits intermédiaires et les préparations terminées. Ces revues permettent de mettre en évidence toute évolution et d’identifier les améliorations à apporter aux produits et aux procédés. Elles alimentent l’analyse globale du risque lié à la préparation et sont normalement menées et documentées selon une périodicité appropriée et justifiée. Elles prennent en compte les revues précédentes. Elles comprennent notamment le suivi des éléments suivants : -Les MPUP et les articles de conditionnement utilisés pour la préparation, notamment ceux provenant de nouvelles sources d’approvisionnement, ainsi que la traçabilité de la chaîne d’approvisionnement des substances actives ; -les résultats des contrôles qualité des préparations terminées ; -les lots non conformes aux spécifications établies ainsi que les investigations correspondantes ; -les déviations significatives et les non-conformités, les investigations correspondantes et l'efficacité des actions correctives et préventives prises en conséquence ; -les modifications intervenues sur les procédés ou sur les méthodes d'analyse ; -les retours, réclamations et rappels liés à des problèmes de qualité ainsi que les investigations correspondantes ; -la pertinence de toute mesure corrective antérieure relative au procédé de préparation ou aux équipements ; -la qualification des principaux équipements et de leurs utilités, par exemple les installations de traitement de l’air, de production et de distribution de l’eau ou de gaz comprimés ; -les contrats et/ou cahiers des charges et/ou plannings de maintenance technique afin de s'assurer qu'ils sont à jour. | C11: =COUNTIF(Référentiel!$L$2:$L$1371,"*, "&A11&",*")
A12: 1.11 | B12: L’appréciation du rapport bénéfice/risque permet d’évaluer les dangers potentiels et sert de base pour décider si des mesures de réduction des risques sont à appliquer, ou si le risque existant peut être accepté. | C12: =COUNTIF(Référentiel!$L$2:$L$1371,"*, "&A12&",*")
A13: 1.12 | B13: Quel que soit le risque associé à la réalisation d'une préparation et préalablement à sa réalisation, une analyse pharmaceutique est réalisée par le pharmacien qui reçoit la demande. Un exemple d’outil d’aide à l’analyse pharmaceutique et réglementaire est proposé (cf. Annexe I). | C13: =COUNTIF(Référentiel!$L$2:$L$1371,"*, "&A13&",*")
... A599: LD3.28 | B599: Après la destruction des médicaments expérimentaux, un certificat daté ou une attestation confirmant la réalisation de cette opération est remis au promoteur. Ces documents identifient clairement, ou permettent d’assurer la traçabilité des lots et/ou des numéros de traitement et/ou des numéros de personnes incluses dans la RIPH concernée, ainsi que les quantités effectivement détruites. | C599: =COUNTIF(Référentiel!$L$2:$L$1371,"*, "&A599&",*")

Sheet Journal
A1: Date | B1: Code | C1: Modification
A2: 09/10/2026 | C2: Colonnes « Sévérité » (Critique / Majeur / Mineur) et « Motif de la sévérité » ajoutées pour les 1 168 questions ; feuille « Sévérités » (répartition et pondération). Grille proposée, à valider.
A3: 08/10/2026 | C3: Version 2026-10-08 : « S 01 » était une erreur de numérotation ; elle devient Q001 et toutes les questions sont décalées d'un rang (Q001 → Q002 … Q744 → Q745), sous-questions, questions chapeau et conditions comprises.
A4: 08/10/2026 | C4: Colonne « Ancien code » : code de chaque question dans la version 2026-10-07 (les réponses déjà saisies suivent leur question à l'import).
A5: 07/10/2026 | C5: Fichier maître créé à partir de « auto_inspection_BPP_version_jft_07_10_2026_v10.xlsx » (feuille « ordre question »).
A6: 07/10/2026 | C6: Une ligne par élément (au lieu d'une ligne par couple question × référence) ; références regroupées en colonne J.
A7: 07/10/2026 | C7: Niveaux de titres explicités en colonne C (1 = chapitre … 5), repris de la structure validée dans l'outil.
A8: 07/10/2026 | C8: Titres : accents et libellés normalisés (ex. « SYTEME » → « SYSTÈME », « LD1 » → « Préparations stériles - LD1 »).
A9: 07/10/2026 | C9: Questions renumérotées par rapport à la version initiale de l'outil (suppression du trou Q102, fusion Q641/Q642).
A10: 07/10/2026 | B10: Q641 | C10: Fusion des anciennes Q641 et Q642 (intitulé identique, Q640 en version 2026-10-07) ; références LD2.013 rattachées.
A11: 07/10/2026 | C11: Références mal saisies normalisées : 1.7 → 1.07, 5.7 → 5.07, 5.8 → 5.08, 8.1 → 8.01, 8.9 → 8.09, LD1 046 → LD1.046, LD1 116. → LD1.116, LD2.06 → LD2.006, LD2.07 → LD2.007, LD2.034. → LD2.034 (pour 1.7 et 5.8 / LD1.046 / LD1.116, le texte de la forme correcte, déjà présent, est conservé).
A12: 07/10/2026 | B12: Q624.04.01 | C12: Anciennes Q624.05 / Q624.06 (« cytotoxiques », « non cytotoxiques ») rattachées à l'intitulé commun Q623.04.
A13: 07/10/2026 | B13: Q087 | C13: Condition « Q085 » complétée en « Q086-OUI » (réponse attendue explicitée)
A14: 07/10/2026 | B14: Q125 | C14: Condition « Q123 » complétée en « Q124-OUI » (réponse attendue explicitée)
A15: 07/10/2026 | B15: Q126 | C15: Condition « Q123 » complétée en « Q124-OUI » (réponse attendue explicitée)
A16: 07/10/2026 | B16: Q211 | C16: Condition « Q210-OUI » (la question dépendait d'elle-même) remplacée par « Q210-OUI »
A17: 07/10/2026 | B17: Q549.01 | C17: Code « Q548-01 » renuméroté « Q548.01 » (sous-question : séparateur point)
A18: 07/10/2026 | B18: Q549.02 | C18: Code « Q548-02 » renuméroté « Q548.02 » (sous-question : séparateur point)
A19: 07/10/2026 | B19: Q549.03 | C19: Code « Q548-03 » renuméroté « Q548.03 » (sous-question : séparateur point)
A20: 07/10/2026 | B20: Q549.04 | C20: Code « Q548-04 » renuméroté « Q548.04 » (sous-question : séparateur point)
A21: 07/10/2026 | B21: Q549.05 | C21: Code « Q548-05 » renuméroté « Q548.05 » (sous-question : séparateur point)
A22: 07/10/2026 | B22: Q549.06 | C22: Code « Q548-06 » renuméroté « Q548.06 » (sous-question : séparateur point)
A23: 07/10/2026 | B23: Q549.07 | C23: Code « Q548-07 » renuméroté « Q548.07 » (sous-question : séparateur point)
